piracer/__init__.py
piracer/cameras.py
piracer/gamepads.py
piracer/vehicles.py
piracer_py-0.1.1.dist-info/LICENSE
piracer_py-0.1.1.dist-info/METADATA
piracer_py-0.1.1.dist-info/WHEEL
piracer_py-0.1.1.dist-info/top_level.txt
piracer_py-0.1.1.dist-info/RECORD
