Metadata-Version: 2.1
Name: piracer_py
Version: 0.1.1
Summary: Simple abstraction layer for PiRacer and PiRacer Pro
Home-page: https://github.com/twyleg/piracer_py
Author: Torsten Wylegala
Author-email: mail@twyleg.de
License: GPL 3.0
Keywords: piracer embedded abstraction
License-File: LICENSE
